sphinx_jinja2/__init__.py
sphinx_jinja2/_private.py
sphinx_jinja2-0.0.1.dist-info/LICENSE
sphinx_jinja2-0.0.1.dist-info/WHEEL
sphinx_jinja2-0.0.1.dist-info/METADATA
sphinx_jinja2-0.0.1.dist-info/RECORD
